{"success": true, "data": [{"id": "71d1b1a81dc41196f2d867f660195b44", "sport_key": "soccer_epl", "sport_nice": "EPL", "teams": ["Arsenal", "Everton"], "commence_time": 1653231600, "home_team": "Arsenal", "sites": [{"site_key": "betclic", "site_nice": "Betclic", "last_update": 1653221621, "odds": {"h2h": [1.4, 7.5, 5.25]}}, {"site_key": "paddypower", "site_nice": "Paddy Power", "last_update": 1653221621, "odds": {"h2h": [1.33, 7.5, 5.0]}}, {"site_key": "betfair", "site_nice": "Betfair", "last_update": 1653221591, "odds": {"h2h": [1.41, 9.0, 5.5], "h2h_lay": [1.42, 9.2, 5.6]}}, {"site_key": "matchbook", "site_nice": "Matchbook", "last_update": 1653221511, "odds": {"h2h": [1.41, 9.0, 5.5], "h2h_lay": [1.42, 9.2, 5.6]}}, {"site_key": "betvictor", "site_nice": "Bet Victor", "last_update": 1653221653, "odds": {"h2h": [1.36, 8.5, 5.25]}}, {"site_key": "williamhill", "site_nice": "William Hill", "last_update": 1653221408, "odds": {"h2h": [1.36, 8.5, 4.8]}}, {"site_key": "skybet", "site_nice": "Sky Bet", "last_update": 1653221563, "odds": {"h2h": [1.36, 8.0, 5.0]}}, {"site_key": "virginbet", "site_nice": "Virgin Bet", "last_update": 1653221623, "odds": {"h2h": [1.37, 8.0, 5.25]}}, {"site_key": "livescorebet", "site_nice": "LiveScore Bet", "last_update": 1653221598, "odds": {"h2h": [1.37, 8.0, 5.25]}}, {"site_key": "betfred", "site_nice": "Betfred", "last_update": 1653221540, "odds": {"h2h": [1.4, 8.5, 5.0]}}, {"site_key": "marathonbet", "site_nice": "Marathon Bet", "last_update": 1653221593, "odds": {"h2h": [1.4, 8.3, 5.25]}}, {"site_key": "coral", "site_nice": "Coral", "last_update": 1653221623, "odds": {"h2h": [1.4, 8.5, 5.0]}}, {"site_key": "ladbrokes", "site_nice": "Ladbrokes", "last_update": 1653221592, "odds": {"h2h": [1.36, 8.25, 4.8]}}, {"site_key": "boylesports", "site_nice": "BoyleSports", "last_update": 1653221492, "odds": {"h2h": [1.36, 8.0, 5.0]}}, {"site_key": "leovegas", "site_nice": "LeoVegas", "last_update": 1653221652, "odds": {"h2h": [1.34, 8.5, 5.2]}}, {"site_key": "casumo", "site_nice": "Casumo", "last_update": 1653221540, "odds": {"h2h": [1.32, 8.5, 5.2]}}, {"site_key": "unibet", "site_nice": "Unibet", "last_update": 1653221537, "odds": {"h2h": [1.41, 8.8, 5.5]}}, {"site_key": "mrgreen", "site_nice": "Mr Green", "last_update": 1653221512, "odds": {"h2h": [1.35, 8.5, 5.25]}}, {"site_key": "sport888", "site_nice": "888sport", "last_update": 1653221511, "odds": {"h2h": [1.36, 8.5, 5.3]}}], "sites_count": 19}, {"id": "954a39d7c822a24a58c76dd74427310f", "sport_key": "soccer_epl", "sport_nice": "EPL", "teams": ["Brentford", "Leeds United"], "commence_time": 1653231600, "home_team": "Brentford", "sites": [{"site_key": "betclic", "site_nice": "Betclic", "last_update": 1653221621, "odds": {"h2h": [2.3, 2.96, 3.75]}}, {"site_key": "paddypower", "site_nice": "Paddy Power", "last_update": 1653221621, "odds": {"h2h": [2.2, 2.88, 3.6]}}, {"site_key": "betfair", "site_nice": "Betfair", "last_update": 1653221591, "odds": {"h2h": [2.38, 3.05, 3.95], "h2h_lay": [2.4, 3.1, 4.0]}}, {"site_key": "matchbook", "site_nice": "Matchbook", "last_update": 1653221511, "odds": {"h2h": [2.38, 3.05, 3.95], "h2h_lay": [2.42, 3.1, 4.0]}}, {"site_key": "betvictor", "site_nice": "Bet Victor", "last_update": 1653221653, "odds": {"h2h": [2.3, 3.0, 3.7]}}, {"site_key": "williamhill", "site_nice": "William Hill", "last_update": 1653221408, "odds": {"h2h": [2.25, 3.0, 3.5]}}, {"site_key": "skybet", "site_nice": "Sky Bet", "last_update": 1653221563, "odds": {"h2h": [2.25, 2.88, 3.75]}}, {"site_key": "virginbet", "site_nice": "Virgin Bet", "last_update": 1653221623, "odds": {"h2h": [2.25, 2.9, 3.8]}}, {"site_key": "livescorebet", "site_nice": "LiveScore Bet", "last_update": 1653221598, "odds": {"h2h": [2.25, 2.9, 3.8]}}, {"site_key": "betfred", "site_nice": "Betfred", "last_update": 1653221540, "odds": {"h2h": [2.3, 3.0, 3.75]}}, {"site_key": "marathonbet", "site_nice": "Marathon Bet", "last_update": 1653221593, "odds": {"h2h": [2.31, 2.97, 3.92]}}, {"site_key": "coral", "site_nice": "Coral", "last_update": 1653221623, "odds": {"h2h": [2.3, 3.0, 3.7]}}, {"site_key": "ladbrokes", "site_nice": "Ladbrokes", "last_update": 1653221592, "odds": {"h2h": [2.25, 2.9, 3.6]}}, {"site_key": "boylesports", "site_nice": "BoyleSports", "last_update": 1653221492, "odds": {"h2h": [2.25, 2.9, 3.6]}}, {"site_key": "leovegas", "site_nice": "LeoVegas", "last_update": 1653221652, "odds": {"h2h": [2.25, 2.9, 3.75]}}, {"site_key": "casumo", "site_nice": "Casumo", "last_update": 1653221540, "odds": {"h2h": [2.23, 2.88, 3.7]}}, {"site_key": "unibet", "site_nice": "Unibet", "last_update": 1653221537, "odds": {"h2h": [2.36, 3.05, 3.95]}}, {"site_key": "mrgreen", "site_nice": "Mr Green", "last_update": 1653221512, "odds": {"h2h": [2.28, 2.95, 3.8]}}, {"site_key": "sport888", "site_nice": "888sport", "last_update": 1653221511, "odds": {"h2h": [2.28, 2.95, 3.8]}}], "sites_count": 19}, {"id": "2e2522f72ad3a3035e915e7a559b2065", "sport_key": "soccer_epl", "sport_nice": "EPL", "teams": ["Brighton and Hove Albion", "West Ham United"], "commence_time": 1653231600, "home_team": "Brighton and Hove Albion", "sites": [{"site_key": "betclic", "site_nice": "Betclic", "last_update": 1653221621, "odds": {"h2h": [2.59, 2.7, 3.52]}}, {"site_key": "paddypower", "site_nice": "Paddy Power", "last_update": 1653221621, "odds": {"h2h": [2.5, 2.62, 3.4]}}, {"site_key": "betfair", "site_nice": "Betfair", "last_update": 1653221591, "odds": {"h2h": [2.7, 2.82, 3.6], "h2h_lay": [2.72, 2.84, 3.65]}}, {"site_key": "matchbook", "site_nice": "Matchbook", "last_update": 1653221511, "odds": {"h2h": [2.7, 2.84, 3.6], "h2h_lay": [2.72, 2.86, 3.7]}}, {"site_key": "williamhill", "site_nice": "William Hill", "last_update": 1653221408, "odds": {"h2h": [2.5, 2.7, 3.4]}}, {"site_key": "skybet", "site_nice": "Sky Bet", "last_update": 1653221563, "odds": {"h2h": [2.5, 2.62, 3.6]}}, {"site_key": "betfred", "site_nice": "Betfred", "last_update": 1653221540, "odds": {"h2h": [2.6, 2.7, 3.6]}}, {"site_key": "betvictor", "site_nice": "Bet Victor", "last_update": 1653221653, "odds": {"h2h": [2.6, 2.7, 3.5]}}, {"site_key": "virginbet", "site_nice": "Virgin Bet", "last_update": 1653221623, "odds": {"h2h": [2.6, 2.7, 3.5]}}, {"site_key": "livescorebet", "site_nice": "LiveScore Bet", "last_update": 1653221598, "odds": {"h2h": [2.6, 2.7, 3.5]}}, {"site_key": "marathonbet", "site_nice": "Marathon Bet", "last_update": 1653221593, "odds": {"h2h": [2.58, 2.77, 3.62]}}, {"site_key": "coral", "site_nice": "Coral", "last_update": 1653221623, "odds": {"h2h": [2.6, 2.7, 3.5]}}, {"site_key": "ladbrokes", "site_nice": "Ladbrokes", "last_update": 1653221592, "odds": {"h2h": [2.55, 2.65, 3.5]}}, {"site_key": "boylesports", "site_nice": "BoyleSports", "last_update": 1653221492, "odds": {"h2h": [2.5, 2.62, 3.6]}}, {"site_key": "leovegas", "site_nice": "LeoVegas", "last_update": 1653221652, "odds": {"h2h": [2.5, 2.7, 3.45]}}, {"site_key": "casumo", "site_nice": "Casumo", "last_update": 1653221540, "odds": {"h2h": [2.48, 2.65, 3.4]}}, {"site_key": "unibet", "site_nice": "Unibet", "last_update": 1653221537, "odds": {"h2h": [2.65, 2.85, 3.65]}}, {"site_key": "mrgreen", "site_nice": "Mr Green", "last_update": 1653221512, "odds": {"h2h": [2.55, 2.75, 3.5]}}, {"site_key": "sport888", "site_nice": "888sport", "last_update": 1653221511, "odds": {"h2h": [2.55, 2.75, 3.5]}}], "sites_count": 19}, {"id": "fc97a1d33e76eaa2f5b2100a28a79075", "sport_key": "soccer_epl", "sport_nice": "EPL", "teams": ["Burnley", "Newcastle United"], "commence_time": 1653231600, "home_team": "Burnley", "sites": [{"site_key": "betclic", "site_nice": "Betclic", "last_update": 1653221621, "odds": {"h2h": [2.32, 3.25, 3.32]}}, {"site_key": "paddypower", "site_nice": "Paddy Power", "last_update": 1653221621, "odds": {"h2h": [2.25, 3.1, 3.3]}}, {"site_key": "betfair", "site_nice": "Betfair", "last_update": 1653221591, "odds": {"h2h": [2.38, 3.3, 3.5], "h2h_lay": [2.4, 3.4, 3.55]}}, {"site_key": "matchbook", "site_nice": "Matchbook", "last_update": 1653221511, "odds": {"h2h": [2.38, 3.3, 3.5], "h2h_lay": [2.4, 3.4, 3.55]}}, {"site_key": "betvictor", "site_nice": "Bet Victor", "last_update": 1653221653, "odds": {"h2h": [2.3, 3.3, 3.3]}}, {"site_key": "williamhill", "site_nice": "William Hill", "last_update": 1653221408, "odds": {"h2h": [2.3, 3.2, 3.2]}}, {"site_key": "skybet", "site_nice": "Sky Bet", "last_update": 1653221563, "odds": {"h2h": [2.3, 3.1, 3.3]}}, {"site_key": "virginbet", "site_nice": "Virgin Bet", "last_update": 1653221623, "odds": {"h2h": [2.38, 3.2, 3.3]}}, {"site_key": "livescorebet", "site_nice": "LiveScore Bet", "last_update": 1653221598, "odds": {"h2h": [2.38, 3.2, 3.3]}}, {"site_key": "betfred", "site_nice": "Betfred", "last_update": 1653221540, "odds": {"h2h": [2.3, 3.25, 3.4]}}, {"site_key": "marathonbet", "site_nice": "Marathon Bet", "last_update": 1653221593, "odds": {"h2h": [2.38, 3.16, 3.48]}}, {"site_key": "coral", "site_nice": "Coral", "last_update": 1653221623, "odds": {"h2h": [2.3, 3.3, 3.25]}}, {"site_key": "ladbrokes", "site_nice": "Ladbrokes", "last_update": 1653221592, "odds": {"h2h": [2.3, 3.25, 3.2]}}, {"site_key": "boylesports", "site_nice": "BoyleSports", "last_update": 1653221492, "odds": {"h2h": [2.25, 3.2, 3.2]}}, {"site_key": "leovegas", "site_nice": "LeoVegas", "last_update": 1653221652, "odds": {"h2h": [2.28, 3.1, 3.35]}}, {"site_key": "casumo", "site_nice": "Casumo", "last_update": 1653221540, "odds": {"h2h": [2.25, 3.1, 3.3]}}, {"site_key": "unibet", "site_nice": "Unibet", "last_update": 1653221537, "odds": {"h2h": [2.4, 3.3, 3.55]}}, {"site_key": "mrgreen", "site_nice": "Mr Green", "last_update": 1653221512, "odds": {"h2h": [2.3, 3.15, 3.4]}}, {"site_key": "sport888", "site_nice": "888sport", "last_update": 1653221511, "odds": {"h2h": [2.3, 3.15, 3.4]}}], "sites_count": 19}, {"id": "c95f5af858d1d02ea711d360e0502e4b", "sport_key": "soccer_epl", "sport_nice": "EPL", "teams": ["Chelsea", "Watford"], "commence_time": 1653231600, "home_team": "Chelsea", "sites": [{"site_key": "betclic", "site_nice": "Betclic", "last_update": 1653221621, "odds": {"h2h": [1.2, 13.75, 7.35]}}, {"site_key": "paddypower", "site_nice": "Paddy Power", "last_update": 1653221621, "odds": {"h2h": [1.17, 14.0, 7.0]}}, {"site_key": "betvictor", "site_nice": "Bet Victor", "last_update": 1653221653, "odds": {"h2h": [1.2, 13.0, 7.5]}}, {"site_key": "betfair", "site_nice": "Betfair", "last_update": 1653221591, "odds": {"h2h": [1.21, 17.5, 8.0], "h2h_lay": [1.22, 18.5, 8.4]}}, {"site_key": "williamhill", "site_nice": "William Hill", "last_update": 1653221408, "odds": {"h2h": [1.18, 13.0, 7.5]}}, {"site_key": "matchbook", "site_nice": "Matchbook", "last_update": 1653221511, "odds": {"h2h": [1.21, 17.5, 8.0], "h2h_lay": [1.22, 18.5, 8.4]}}, {"site_key": "skybet", "site_nice": "Sky Bet", "last_update": 1653221563, "odds": {"h2h": [1.17, 15.0, 7.5]}}, {"site_key": "virginbet", "site_nice": "Virgin Bet", "last_update": 1653221623, "odds": {"h2h": [1.2, 14.0, 7.5]}}, {"site_key": "livescorebet", "site_nice": "LiveScore Bet", "last_update": 1653221598, "odds": {"h2h": [1.2, 14.0, 7.5]}}, {"site_key": "betfred", "site_nice": "Betfred", "last_update": 1653221540, "odds": {"h2h": [1.2, 15.0, 7.5]}}, {"site_key": "marathonbet", "site_nice": "Marathon Bet", "last_update": 1653221593, "odds": {"h2h": [1.2, 16.25, 7.8]}}, {"site_key": "coral", "site_nice": "Coral", "last_update": 1653221623, "odds": {"h2h": [1.2, 13.0, 7.0]}}, {"site_key": "ladbrokes", "site_nice": "Ladbrokes", "last_update": 1653221592, "odds": {"h2h": [1.18, 13.0, 7.0]}}, {"site_key": "boylesports", "site_nice": "BoyleSports", "last_update": 1653221492, "odds": {"h2h": [1.2, 15.0, 7.0]}}, {"site_key": "leovegas", "site_nice": "LeoVegas", "last_update": 1653221652, "odds": {"h2h": [1.16, 16.0, 7.5]}}, {"site_key": "casumo", "site_nice": "Casumo", "last_update": 1653221540, "odds": {"h2h": [1.15, 16.0, 7.5]}}, {"site_key": "unibet", "site_nice": "Unibet", "last_update": 1653221537, "odds": {"h2h": [1.22, 17.0, 8.0]}}, {"site_key": "mrgreen", "site_nice": "Mr Green", "last_update": 1653221512, "odds": {"h2h": [1.17, 16.0, 7.5]}}, {"site_key": "sport888", "site_nice": "888sport", "last_update": 1653221511, "odds": {"h2h": [1.18, 16.0, 7.5]}}], "sites_count": 19}, {"id": "8fe7c94ece502b69d3239ecbfa4dc76b", "sport_key": "soccer_epl", "sport_nice": "EPL", "teams": ["Leicester City", "Southampton"], "commence_time": 1653231600, "home_team": "Leicester City", "sites": [{"site_key": "betclic", "site_nice": "Betclic", "last_update": 1653221621, "odds": {"h2h": [1.78, 4.15, 4.2]}}, {"site_key": "paddypower", "site_nice": "Paddy Power", "last_update": 1653221621, "odds": {"h2h": [1.73, 4.2, 4.0]}}, {"site_key": "betfair", "site_nice": "Betfair", "last_update": 1653221591, "odds": {"h2h": [1.81, 4.5, 4.3], "h2h_lay": [1.82, 4.6, 4.4]}}, {"site_key": "matchbook", "site_nice": "Matchbook", "last_update": 1653221511, "odds": {"h2h": [1.81, 4.5, 4.3], "h2h_lay": [1.82, 4.6, 4.4]}}, {"site_key": "betvictor", "site_nice": "Bet Victor", "last_update": 1653221653, "odds": {"h2h": [1.75, 4.33, 4.2]}}, {"site_key": "williamhill", "site_nice": "William Hill", "last_update": 1653221408, "odds": {"h2h": [1.8, 4.2, 3.9]}}, {"site_key": "virginbet", "site_nice": "Virgin Bet", "last_update": 1653221623, "odds": {"h2h": [1.77, 4.2, 4.2]}}, {"site_key": "livescorebet", "site_nice": "LiveScore Bet", "last_update": 1653221598, "odds": {"h2h": [1.77, 4.2, 4.2]}}, {"site_key": "skybet", "site_nice": "Sky Bet", "last_update": 1653221563, "odds": {"h2h": [1.73, 4.33, 4.0]}}, {"site_key": "betfred", "site_nice": "Betfred", "last_update": 1653221540, "odds": {"h2h": [1.8, 4.33, 4.2]}}, {"site_key": "marathonbet", "site_nice": "Marathon Bet", "last_update": 1653221593, "odds": {"h2h": [1.81, 4.2, 4.3]}}, {"site_key": "coral", "site_nice": "Coral", "last_update": 1653221623, "odds": {"h2h": [1.75, 4.33, 4.0]}}, {"site_key": "ladbrokes", "site_nice": "Ladbrokes", "last_update": 1653221592, "odds": {"h2h": [1.75, 4.25, 4.0]}}, {"site_key": "boylesports", "site_nice": "BoyleSports", "last_update": 1653221492, "odds": {"h2h": [1.8, 4.0, 4.0]}}, {"site_key": "sport888", "site_nice": "888sport", "last_update": 1653221511, "odds": {"h2h": [1.75, 4.35, 4.2]}}, {"site_key": "leovegas", "site_nice": "LeoVegas", "last_update": 1653221652, "odds": {"h2h": [1.72, 4.3, 4.1]}}, {"site_key": "casumo", "site_nice": "Casumo", "last_update": 1653221540, "odds": {"h2h": [1.7, 4.25, 4.1]}}, {"site_key": "mrgreen", "site_nice": "Mr Green", "last_update": 1653221512, "odds": {"h2h": [1.74, 4.3, 4.2]}}, {"site_key": "unibet", "site_nice": "Unibet", "last_update": 1653221537, "odds": {"h2h": [1.81, 4.5, 4.35]}}], "sites_count": 19}, {"id": "d6b0b1dc07e70b03c39b7586cb344bbc", "sport_key": "soccer_epl", "sport_nice": "EPL", "teams": ["Crystal Palace", "Manchester United"], "commence_time": 1653231600, "home_team": "Crystal Palace", "sites": [{"site_key": "betclic", "site_nice": "Betclic", "last_update": 1653221621, "odds": {"h2h": [2.96, 2.4, 3.5]}}, {"site_key": "paddypower", "site_nice": "Paddy Power", "last_update": 1653221621, "odds": {"h2h": [2.8, 2.3, 3.5]}}, {"site_key": "betfair", "site_nice": "Betfair", "last_update": 1653221591, "odds": {"h2h": [3.0, 2.48, 3.7], "h2h_lay": [3.05, 2.5, 3.75]}}, {"site_key": "betvictor", "site_nice": "Bet Victor", "last_update": 1653221653, "odds": {"h2h": [3.0, 2.4, 3.5]}}, {"site_key": "williamhill", "site_nice": "William Hill", "last_update": 1653221408, "odds": {"h2h": [2.9, 2.38, 3.4]}}, {"site_key": "virginbet", "site_nice": "Virgin Bet", "last_update": 1653221623, "odds": {"h2h": [2.9, 2.4, 3.6]}}, {"site_key": "livescorebet", "site_nice": "LiveScore Bet", "last_update": 1653221598, "odds": {"h2h": [2.9, 2.4, 3.6]}}, {"site_key": "skybet", "site_nice": "Sky Bet", "last_update": 1653221563, "odds": {"h2h": [2.88, 2.3, 3.6]}}, {"site_key": "matchbook", "site_nice": "Matchbook", "last_update": 1653221511, "odds": {"h2h": [3.0, 2.48, 3.7], "h2h_lay": [3.05, 2.52, 3.75]}}, {"site_key": "betfred", "site_nice": "Betfred", "last_update": 1653221540, "odds": {"h2h": [3.0, 2.4, 3.6]}}, {"site_key": "marathonbet", "site_nice": "Marathon Bet", "last_update": 1653221593, "odds": {"h2h": [3.02, 2.45, 3.5]}}, {"site_key": "coral", "site_nice": "Coral", "last_update": 1653221623, "odds": {"h2h": [2.9, 2.4, 3.5]}}, {"site_key": "ladbrokes", "site_nice": "Ladbrokes", "last_update": 1653221592, "odds": {"h2h": [2.9, 2.4, 3.4]}}, {"site_key": "boylesports", "site_nice": "BoyleSports", "last_update": 1653221492, "odds": {"h2h": [2.88, 2.38, 3.5]}}, {"site_key": "sport888", "site_nice": "888sport", "last_update": 1653221511, "odds": {"h2h": [2.9, 2.38, 3.6]}}, {"site_key": "leovegas", "site_nice": "LeoVegas", "last_update": 1653221652, "odds": {"h2h": [2.85, 2.35, 3.55]}}, {"site_key": "casumo", "site_nice": "Casumo", "last_update": 1653221540, "odds": {"h2h": [2.8, 2.32, 3.55]}}, {"site_key": "mrgreen", "site_nice": "Mr Green", "last_update": 1653221512, "odds": {"h2h": [2.88, 2.38, 3.6]}}, {"site_key": "unibet", "site_nice": "Unibet", "last_update": 1653221537, "odds": {"h2h": [3.0, 2.47, 3.75]}}], "sites_count": 19}, {"id": "8e09c507f1bb54b0ee9282bc67c26a93", "sport_key": "soccer_epl", "sport_nice": "EPL", "teams": ["Liverpool", "Wolverhampton Wanderers"], "commence_time": 1653231600, "home_team": "Liverpool", "sites": [{"site_key": "betclic", "site_nice": "Betclic", "last_update": 1653221621, "odds": {"h2h": [1.14, 18.25, 9.05]}}, {"site_key": "paddypower", "site_nice": "Paddy Power", "last_update": 1653221621, "odds": {"h2h": [1.11, 18.0, 9.0]}}, {"site_key": "betvictor", "site_nice": "Bet Victor", "last_update": 1653221653, "odds": {"h2h": [1.15, 18.0, 8.5]}}, {"site_key": "betfair", "site_nice": "Betfair", "last_update": 1653221591, "odds": {"h2h": [1.16, 23.0, 10.0], "h2h_lay": [1.17, 24.0, 10.5]}}, {"site_key": "williamhill", "site_nice": "William Hill", "last_update": 1653221408, "odds": {"h2h": [1.14, 19.0, 8.0]}}, {"site_key": "skybet", "site_nice": "Sky Bet", "last_update": 1653221563, "odds": {"h2h": [1.12, 17.0, 9.0]}}, {"site_key": "matchbook", "site_nice": "Matchbook", "last_update": 1653221511, "odds": {"h2h": [1.16, 23.0, 10.0], "h2h_lay": [1.17, 24.0, 10.5]}}, {"site_key": "virginbet", "site_nice": "Virgin Bet", "last_update": 1653221623, "odds": {"h2h": [1.13, 19.0, 9.5]}}, {"site_key": "livescorebet", "site_nice": "LiveScore Bet", "last_update": 1653221598, "odds": {"h2h": [1.13, 19.0, 9.5]}}, {"site_key": "betfred", "site_nice": "Betfred", "last_update": 1653221540, "odds": {"h2h": [1.14, 21.0, 9.5]}}, {"site_key": "marathonbet", "site_nice": "Marathon Bet", "last_update": 1653221593, "odds": {"h2h": [1.16, 22.0, 10.25]}}, {"site_key": "coral", "site_nice": "Coral", "last_update": 1653221623, "odds": {"h2h": [1.14, 23.0, 9.0]}}, {"site_key": "ladbrokes", "site_nice": "Ladbrokes", "last_update": 1653221592, "odds": {"h2h": [1.13, 19.0, 8.25]}}, {"site_key": "boylesports", "site_nice": "BoyleSports", "last_update": 1653221492, "odds": {"h2h": [1.12, 19.0, 7.0]}}, {"site_key": "leovegas", "site_nice": "LeoVegas", "last_update": 1653221652, "odds": {"h2h": [1.11, 19.0, 9.5]}}, {"site_key": "casumo", "site_nice": "Casumo", "last_update": 1653221540, "odds": {"h2h": [1.1, 19.0, 9.5]}}, {"site_key": "mrgreen", "site_nice": "Mr Green", "last_update": 1653221512, "odds": {"h2h": [1.12, 20.0, 10.0]}}, {"site_key": "unibet", "site_nice": "Unibet", "last_update": 1653221537, "odds": {"h2h": [1.16, 21.0, 10.5]}}, {"site_key": "sport888", "site_nice": "888sport", "last_update": 1653221511, "odds": {"h2h": [1.12, 20.0, 10.0]}}], "sites_count": 19}, {"id": "f868727684903c3c5d875618d1756050", "sport_key": "soccer_epl", "sport_nice": "EPL", "teams": ["Aston Villa", "Manchester City"], "commence_time": 1653231600, "home_team": "Manchester City", "sites": [{"site_key": "betclic", "site_nice": "Betclic", "last_update": 1653221621, "odds": {"h2h": [14.5, 1.19, 7.7]}}, {"site_key": "paddypower", "site_nice": "Paddy Power", "last_update": 1653221621, "odds": {"h2h": [15.0, 1.14, 7.5]}}, {"site_key": "betfair", "site_nice": "Betfair", "last_update": 1653221591, "odds": {"h2h": [19.0, 1.2, 8.4], "h2h_lay": [19.5, 1.21, 8.6]}}, {"site_key": "betvictor", "site_nice": "Bet Victor", "last_update": 1653221653, "odds": {"h2h": [17.0, 1.17, 8.0]}}, {"site_key": "williamhill", "site_nice": "William Hill", "last_update": 1653221408, "odds": {"h2h": [17.0, 1.17, 6.5]}}, {"site_key": "skybet", "site_nice": "Sky Bet", "last_update": 1653221563, "odds": {"h2h": [17.0, 1.14, 8.0]}}, {"site_key": "matchbook", "site_nice": "Matchbook", "last_update": 1653221511, "odds": {"h2h": [19.0, 1.2, 8.4], "h2h_lay": [19.5, 1.21, 8.6]}}, {"site_key": "virginbet", "site_nice": "Virgin Bet", "last_update": 1653221623, "odds": {"h2h": [15.0, 1.18, 8.0]}}, {"site_key": "livescorebet", "site_nice": "LiveScore Bet", "last_update": 1653221598, "odds": {"h2h": [15.0, 1.18, 8.0]}}, {"site_key": "betfred", "site_nice": "Betfred", "last_update": 1653221540, "odds": {"h2h": [17.0, 1.18, 8.0]}}, {"site_key": "marathonbet", "site_nice": "Marathon Bet", "last_update": 1653221593, "odds": {"h2h": [19.5, 1.2, 8.6]}}, {"site_key": "coral", "site_nice": "Coral", "last_update": 1653221623, "odds": {"h2h": [17.0, 1.18, 7.5]}}, {"site_key": "ladbrokes", "site_nice": "Ladbrokes", "last_update": 1653221592, "odds": {"h2h": [16.0, 1.17, 6.8]}}, {"site_key": "boylesports", "site_nice": "BoyleSports", "last_update": 1653221492, "odds": {"h2h": [13.0, 1.18, 7.5]}}, {"site_key": "leovegas", "site_nice": "LeoVegas", "last_update": 1653221652, "odds": {"h2h": [18.0, 1.14, 8.0]}}, {"site_key": "casumo", "site_nice": "Casumo", "last_update": 1653221540, "odds": {"h2h": [17.0, 1.13, 8.0]}}, {"site_key": "mrgreen", "site_nice": "Mr Green", "last_update": 1653221512, "odds": {"h2h": [18.0, 1.15, 8.0]}}, {"site_key": "unibet", "site_nice": "Unibet", "last_update": 1653221537, "odds": {"h2h": [19.0, 1.2, 8.5]}}, {"site_key": "sport888", "site_nice": "888sport", "last_update": 1653221511, "odds": {"h2h": [18.0, 1.16, 8.0]}}], "sites_count": 19}, {"id": "63cd71feb9ac8e836d6cc1efe61cc577", "sport_key": "soccer_epl", "sport_nice": "EPL", "teams": ["Norwich City", "Tottenham Hotspur"], "commence_time": 1653231600, "home_team": "Norwich City", "sites": [{"site_key": "betclic", "site_nice": "Betclic", "last_update": 1653221621, "odds": {"h2h": [9.5, 1.31, 5.8]}}, {"site_key": "paddypower", "site_nice": "Paddy Power", "last_update": 1653221621, "odds": {"h2h": [10.0, 1.25, 5.5]}}, {"site_key": "betfair", "site_nice": "Betfair", "last_update": 1653221591, "odds": {"h2h": [11.5, 1.33, 6.0], "h2h_lay": [12.0, 1.34, 6.2]}}, {"site_key": "betvictor", "site_nice": "Bet Victor", "last_update": 1653221653, "odds": {"h2h": [10.5, 1.29, 6.0]}}, {"site_key": "williamhill", "site_nice": "William Hill", "last_update": 1653221408, "odds": {"h2h": [10.0, 1.29, 5.5]}}, {"site_key": "matchbook", "site_nice": "Matchbook", "last_update": 1653221511, "odds": {"h2h": [11.5, 1.33, 6.0], "h2h_lay": [12.0, 1.34, 6.2]}}, {"site_key": "virginbet", "site_nice": "Virgin Bet", "last_update": 1653221623, "odds": {"h2h": [10.5, 1.29, 6.0]}}, {"site_key": "livescorebet", "site_nice": "LiveScore Bet", "last_update": 1653221598, "odds": {"h2h": [10.5, 1.29, 6.0]}}, {"site_key": "skybet", "site_nice": "Sky Bet", "last_update": 1653221563, "odds": {"h2h": [10.5, 1.25, 5.75]}}, {"site_key": "betfred", "site_nice": "Betfred", "last_update": 1653221540, "odds": {"h2h": [11.0, 1.3, 6.0]}}, {"site_key": "marathonbet", "site_nice": "Marathon Bet", "last_update": 1653221593, "odds": {"h2h": [10.75, 1.31, 5.95]}}, {"site_key": "coral", "site_nice": "Coral", "last_update": 1653221623, "odds": {"h2h": [9.0, 1.3, 5.5]}}, {"site_key": "ladbrokes", "site_nice": "Ladbrokes", "last_update": 1653221592, "odds": {"h2h": [9.25, 1.3, 5.4]}}, {"site_key": "boylesports", "site_nice": "BoyleSports", "last_update": 1653221492, "odds": {"h2h": [10.0, 1.29, 5.5]}}, {"site_key": "leovegas", "site_nice": "LeoVegas", "last_update": 1653221652, "odds": {"h2h": [11.5, 1.25, 5.8]}}, {"site_key": "casumo", "site_nice": "Casumo", "last_update": 1653221540, "odds": {"h2h": [11.0, 1.24, 5.75]}}, {"site_key": "mrgreen", "site_nice": "Mr Green", "last_update": 1653221512, "odds": {"h2h": [11.5, 1.27, 5.8]}}, {"site_key": "unibet", "site_nice": "Unibet", "last_update": 1653221537, "odds": {"h2h": [12.0, 1.32, 6.15]}}, {"site_key": "sport888", "site_nice": "888sport", "last_update": 1653221511, "odds": {"h2h": [11.5, 1.27, 6.0]}}], "sites_count": 19}]}